Metadata-Version: 1.0
Name: helloworld-project
Version: 0.0.1
Summary: My Package hello_world
Home-page: UNKNOWN
Author: mmorfii
Author-email: dasha.zueva@list.ru
License: UNKNOWN
Platform: UNKNOWN
